prototest/__init__.py
prototest/modelfile_v2_pb2.py
prototest/modelfile_v2_pb2.pyi
prototest/py.typed
testprotototo-0.1.0.dist-info/METADATA
testprotototo-0.1.0.dist-info/WHEEL
testprotototo-0.1.0.dist-info/licenses/LICENSE
testprotototo-0.1.0.dist-info/RECORD
