Metadata-Version: 2.1
Name: testprotototo
Version: 0.1.0
License-File: LICENSE
Requires-Python: >=3.10
Requires-Dist: protobuf==3.20.3
